Metadata-Version: 2.1
Name: singularitylib
Version: 0.0.7
Summary: 奇点库，功能整合
Home-page: https://github.com/
Author: Singularity
Author-email: zhw521024@outlook.com
License: UNKNOWN
Platform: UNKNOWN
Classifier: Programming Language :: Python :: 3
Classifier: License :: OSI Approved :: MIT License
Classifier: Operating System :: OS Independent
